{
    "en": {
        "title": "Pledge of Allegiance to the National Flag of Sri Lanka",
        "content": "## I salute the National Flag of Sri Lanka,\n ## Which signifies the independence of \n ## my country \n ## And stands for all its people, \n ## United as one Nation \n ## I pledge allegiance to Sri Lanka \n ## And undertake to work,\n ## Towards its peace and prosperity \n ## in a spirit of tolerance and love"
    },
    "si": {
        "title": "ජාතික කොඩියේ පක්ෂපාතභාවයේ ප්\u200Dරතිඥාව",
        "content": "## මාගේ රටේ නිදහස පිලිබිඹු කරමින් \n ## එහි එකම ජනතාවක් ලෙස \n ## එක්සත් සියලු ජනයා වෙනුවෙන් නැගෙන \n ## ශ\u200D්\u200Dරී ලංකා ජාතික කොඩියට \n ## මාගේ නමස්කාරය වේවා \n ## ශ\u200D්\u200Dරී ලංකා මාතාව කෙරෙහි මාගේ \n ## පක්ෂපාතභාවය සඳහා \n ## ප\u200D්\u200Dරතිඥා දෙමින්, කරුණා මෛත\u200D්\u200Dරී සිතින් \n ## එහි සාමය හා සෞභාග්\u200Dයය \n ## ගොඩනැගීමට ඉදිරිපත් වෙමි.",
    }
}
